bnet_toolbox/__init__.py
bnet_toolbox/tools.py
bnet_toolbox-0.0.4.dist-info/LICENSE
bnet_toolbox-0.0.4.dist-info/METADATA
bnet_toolbox-0.0.4.dist-info/WHEEL
bnet_toolbox-0.0.4.dist-info/entry_points.txt
bnet_toolbox-0.0.4.dist-info/top_level.txt
bnet_toolbox-0.0.4.dist-info/RECORD
