Metadata-Version: 2.1
Name: bnet_toolbox
Version: 0.0.4
Summary: A command-line toolbox for interacting with the Battle.net client and Agent
Author-email: Ghostopheles <ghost@ghst.tools>
License: This is free and unencumbered software released into the public domain.
Project-URL: Homepage, https://github.com/Ghostopheles/bnet-toolbox
Project-URL: Repository, https://github.com/Ghostopheles/bnet-toolbox.git
Project-URL: Issues, https://github.com/Ghostopheles/bnet-toolbox/issues
Classifier: Development Status :: 3 - Alpha
Classifier: Intended Audience :: Developers
Classifier: License :: Public Domain
Classifier: Programming Language :: Python :: 3
Classifier: Programming Language :: Python :: 3 :: Only
Classifier: Programming Language :: Python :: 3.12
Requires-Python: >=3.11
License-File: LICENSE
Requires-Dist: httpx
Requires-Dist: typer
